{".class": "MypyFile", "_fullname": "awswrangler.distributed.ray", "future_import_flags": [], "is_partial_stub_package": false, "is_stub": false, "names": {".class": "SymbolTable", "RayLogger": {".class": "SymbolTableNode", "cross_ref": "awswrangler.distributed.ray._core.RayLogger", "kind": "Gdef"}, "__all__": {".class": "SymbolTableNode", "kind": "Gdef", "module_public": false, "node": {".class": "Var", "flags": ["is_inferred", "has_explicit_value"], "fullname": "awswrangler.distributed.ray.__all__", "name": "__all__", "type": {".class": "Instance", "args": ["builtins.str"], "type_ref": "builtins.list"}}}, "__annotations__": {".class": "SymbolTableNode", "kind": "Gdef", "module_public": false, "node": {".class": "Var", "flags": ["is_ready"], "fullname": "awswrangler.distributed.ray.__annotations__", "name": "__annotations__", "type": {".class": "Instance", "args": ["builtins.str", {".class": "AnyType", "missing_import_name": null, "source_any": null, "type_of_any": 6}], "type_ref": "builtins.dict"}}}, "__doc__": {".class": "SymbolTableNode", "kind": "Gdef", "module_public": false, "node": {".class": "Var", "flags": ["is_ready"], "fullname": "awswrangler.distributed.ray.__doc__", "name": "__doc__", "type": "builtins.str"}}, "__file__": {".class": "SymbolTableNode", "kind": "Gdef", "module_public": false, "node": {".class": "Var", "flags": ["is_ready"], "fullname": "awswrangler.distributed.ray.__file__", "name": "__file__", "type": "builtins.str"}}, "__name__": {".class": "SymbolTableNode", "kind": "Gdef", "module_public": false, "node": {".class": "Var", "flags": ["is_ready"], "fullname": "awswrangler.distributed.ray.__name__", "name": "__name__", "type": "builtins.str"}}, "__package__": {".class": "SymbolTableNode", "kind": "Gdef", "module_public": false, "node": {".class": "Var", "flags": ["is_ready"], "fullname": "awswrangler.distributed.ray.__package__", "name": "__package__", "type": "builtins.str"}}, "__path__": {".class": "SymbolTableNode", "kind": "Gdef", "module_public": false, "node": {".class": "Var", "flags": ["is_ready"], "fullname": "awswrangler.distributed.ray.__path__", "name": "__path__", "type": {".class": "Instance", "args": ["builtins.str"], "type_ref": "builtins.list"}}}, "initialize_ray": {".class": "SymbolTableNode", "cross_ref": "awswrangler.distributed.ray._core.initialize_ray", "kind": "Gdef"}, "ray_get": {".class": "SymbolTableNode", "cross_ref": "awswrangler.distributed.ray._core.ray_get", "kind": "Gdef"}, "ray_logger": {".class": "SymbolTableNode", "cross_ref": "awswrangler.distributed.ray._core.ray_logger", "kind": "Gdef"}, "ray_remote": {".class": "SymbolTableNode", "cross_ref": "awswrangler.distributed.ray._core.ray_remote", "kind": "Gdef"}}, "path": "/Volumes/workplace/github.com/aws-sdk-pandas/awswrangler/distributed/ray/__init__.py"}