{
    "queries": [
        {
            "id": "a312d808-ef31-4e2e-adbd-ee66e819741a",
            "name": "IOT platform - turbine status",
            "description": null,
            "query": "select *, CASE WHEN prediction = 'ok' THEN 'Healthy' ELSE CONCAT('Faulty (', prediction, ')') END as status from dbdemos_lakehouse_iot.current_turbine_metrics where turbine_id= '{{ turbine_id }}'",
            "options": {
                "parent": "folders/2218726451409697",
                "apply_auto_limit": true,
                "folder_node_status": "ACTIVE",
                "folder_node_internal_name": "tree/2218726451419679",
                "visualization_control_order": [
                    "turbine_id"
                ],
                "catalog": "hive_metastore",
                "schema": "dbdemos_lakehouse_iot",
                "parameters": [
                    {
                        "queryId": "09520323-73ae-4caa-a43e-6a497723b53e",
                        "title": "turbine_id",
                        "name": "turbine_id",
                        "type": "query",
                        "global": false,
                        "locals": [],
                        "urlPrefix": "p_",
                        "$$value": "60252b8d-2cd9-f51a-10c3-13bd6478a399"
                    }
                ]
            },
            "visualizations": [
                {
                    "id": "0d972d3c-2093-4689-bd4d-8792964381b7",
                    "type": "COUNTER",
                    "name": "Status",
                    "description": "",
                    "options": {
                        "counterLabel": "Status",
                        "counterColName": "status",
                        "rowNumber": 1,
                        "targetRowNumber": 1,
                        "stringDecimal": 0,
                        "stringDecChar": ".",
                        "stringThouSep": ",",
                        "tooltipFormat": "0,0.000",
                        "condensed": true,
                        "withRowNumber": true
                    },
                    "query_plan": null
                },
                {
                    "id": "18052038-d5c7-4bb5-ad06-4e9721a2157e",
                    "type": "TABLE",
                    "name": "Results",
                    "description": "",
                    "options": {
                        "version": 2
                    },
                    "query_plan": null
                },
                {
                    "id": "7cca4f40-d382-4e6a-94b3-3133a89456ea",
                    "type": "MAP",
                    "name": "Map",
                    "description": "",
                    "options": {
                        "latColName": "lat",
                        "lonColName": "long",
                        "groups": {},
                        "mapTileUrl": "//{s}.tile.openstreetmap.org/{z}/{x}/{y}.png",
                        "clusterMarkers": true,
                        "customizeMarkers": false,
                        "iconShape": "marker",
                        "iconFont": "circle",
                        "foregroundColor": "#ffffff",
                        "backgroundColor": "#356AFF",
                        "borderColor": "#356AFF",
                        "bounds": {
                            "_southWest": {
                                "lat": 15.263594052844502,
                                "lng": -127.63517057586465
                            },
                            "_northEast": {
                                "lat": 55.21684818263305,
                                "lng": -68.35294401336463
                            }
                        },
                        "tooltip": {
                            "enabled": false,
                            "template": ""
                        },
                        "popup": {
                            "enabled": true,
                            "template": ""
                        },
                        "showPlotlyControls": true,
                        "condensed": true,
                        "withRowNumber": true
                    },
                    "query_plan": null
                },
                {
                    "id": "ad07eafb-0a5b-418a-a85b-f8032b4a9c19",
                    "type": "TABLE",
                    "name": "Results",
                    "description": "",
                    "options": {
                        "version": 2
                    },
                    "query_plan": null
                },
                {
                    "id": "aef2e0a6-2265-41ec-8a01-1310cd97c40c",
                    "type": "COUNTER",
                    "name": "Model",
                    "description": "",
                    "options": {
                        "counterLabel": "Turbine model",
                        "counterColName": "model",
                        "rowNumber": 1,
                        "targetRowNumber": 1,
                        "stringDecimal": 0,
                        "stringDecChar": ".",
                        "stringThouSep": ",",
                        "tooltipFormat": "0,0.000"
                    },
                    "query_plan": null
                },
                {
                    "id": "ca63688a-7d8c-40b4-9177-c891408e8799",
                    "type": "COUNTER",
                    "name": "energy",
                    "description": "",
                    "options": {
                        "counterLabel": "Current energy produced",
                        "counterColName": "avg_energy",
                        "rowNumber": 1,
                        "targetRowNumber": 1,
                        "stringDecimal": 2,
                        "stringDecChar": ".",
                        "stringThouSep": ",",
                        "tooltipFormat": "0,0.000",
                        "stringPrefix": "",
                        "stringSuffix": " MW",
                        "condensed": true,
                        "withRowNumber": true
                    },
                    "query_plan": null
                }
            ]
        },
        {
            "id": "c1ddb488-db7b-4126-bee6-9fb6b17caa37",
            "name": "IOT platform - turbine sensors",
            "description": null,
            "query": "select * from dbdemos_lakehouse_iot.sensor_bronze where turbine_id= '{{ turbine_id }}'",
            "options": {
                "parent": "folders/2218726451409697",
                "apply_auto_limit": true,
                "folder_node_status": "ACTIVE",
                "folder_node_internal_name": "tree/2218726451419678",
                "visualization_control_order": [
                    "turbine_id"
                ],
                "catalog": "hive_metastore",
                "schema": "dbdemos_lakehouse_iot",
                "parameters": [
                    {
                        "queryId": "09520323-73ae-4caa-a43e-6a497723b53e",
                        "title": "Turbine id",
                        "name": "turbine_id",
                        "type": "query",
                        "locals": [],
                        "urlPrefix": "p_",
                        "$$value": "60252b8d-2cd9-f51a-10c3-13bd6478a399"
                    }
                ]
            },
            "visualizations": [
                {
                    "id": "2c8acc2b-b920-43a6-9b50-c7a379ca3af2",
                    "type": "TABLE",
                    "name": "Results",
                    "description": "",
                    "options": {
                        "version": 2
                    },
                    "query_plan": null
                },
                {
                    "id": "47f41294-0a31-4e1b-97fe-9d07e885fc7c",
                    "type": "CHART",
                    "name": "Sensor E",
                    "description": "",
                    "options": {
                        "version": 2,
                        "globalSeriesType": "line",
                        "sortX": true,
                        "sortY": true,
                        "legend": {
                            "traceorder": "normal"
                        },
                        "xAxis": {
                            "type": "-",
                            "labels": {
                                "enabled": true
                            }
                        },
                        "yAxis": [
                            {
                                "type": "-"
                            },
                            {
                                "type": "-",
                                "opposite": true
                            }
                        ],
                        "alignYAxesAtZero": true,
                        "error_y": {
                            "type": "data",
                            "visible": true
                        },
                        "series": {
                            "stacking": null,
                            "error_y": {
                                "type": "data",
                                "visible": true
                            }
                        },
                        "seriesOptions": {
                            "column_e6e50d1614596": {
                                "yAxis": 0,
                                "type": "line",
                                "color": "#97D8C4"
                            }
                        },
                        "valuesOptions": {},
                        "direction": {
                            "type": "counterclockwise"
                        },
                        "sizemode": "diameter",
                        "coefficient": 1,
                        "numberFormat": "0,0[.]00000",
                        "percentFormat": "0[.]00%",
                        "textFormat": "",
                        "missingValuesAsZero": true,
                        "useAggregationsUi": true,
                        "swappedAxes": false,
                        "dateTimeFormat": "YYYY-MM-DD HH:mm",
                        "showDataLabels": false,
                        "columnConfigurationMap": {
                            "x": {
                                "column": "timestamp",
                                "id": "column_e6e50d1614597"
                            },
                            "y": [
                                {
                                    "id": "column_e6e50d1614596",
                                    "column": "sensor_E",
                                    "transform": "SUM"
                                }
                            ]
                        },
                        "isAggregationOn": true,
                        "condensed": true,
                        "withRowNumber": true,
                        "hideYAxes": true
                    },
                    "query_plan": {
                        "selects": [
                            {
                                "column": "timestamp"
                            },
                            {
                                "function": "SUM",
                                "args": [
                                    {
                                        "column": "sensor_E"
                                    }
                                ],
                                "alias": "column_e6e50d1614596"
                            }
                        ],
                        "groups": [
                            {
                                "column": "timestamp"
                            }
                        ]
                    }
                },
                {
                    "id": "5277fafd-49bb-447c-9f59-697059c3293a",
                    "type": "CHART",
                    "name": "Sensor F",
                    "description": "",
                    "options": {
                        "version": 2,
                        "globalSeriesType": "line",
                        "sortX": true,
                        "sortY": true,
                        "legend": {
                            "traceorder": "normal"
                        },
                        "xAxis": {
                            "type": "-",
                            "labels": {
                                "enabled": true
                            }
                        },
                        "yAxis": [
                            {
                                "type": "-"
                            },
                            {
                                "type": "-",
                                "opposite": true
                            }
                        ],
                        "alignYAxesAtZero": true,
                        "error_y": {
                            "type": "data",
                            "visible": true
                        },
                        "series": {
                            "stacking": null,
                            "error_y": {
                                "type": "data",
                                "visible": true
                            }
                        },
                        "seriesOptions": {
                            "column_e6e50d1615248": {
                                "yAxis": 0,
                                "type": "line",
                                "color": "#F4B942"
                            }
                        },
                        "valuesOptions": {},
                        "direction": {
                            "type": "counterclockwise"
                        },
                        "sizemode": "diameter",
                        "coefficient": 1,
                        "numberFormat": "0,0[.]00000",
                        "percentFormat": "0[.]00%",
                        "textFormat": "",
                        "missingValuesAsZero": true,
                        "useAggregationsUi": true,
                        "swappedAxes": false,
                        "dateTimeFormat": "YYYY-MM-DD HH:mm",
                        "showDataLabels": false,
                        "columnConfigurationMap": {
                            "x": {
                                "column": "timestamp",
                                "id": "column_e6e50d1615246"
                            },
                            "y": [
                                {
                                    "id": "column_e6e50d1615248",
                                    "column": "sensor_F",
                                    "transform": "SUM"
                                }
                            ]
                        },
                        "isAggregationOn": true,
                        "hideYAxes": true,
                        "condensed": true,
                        "withRowNumber": true
                    },
                    "query_plan": {
                        "selects": [
                            {
                                "column": "timestamp"
                            },
                            {
                                "function": "SUM",
                                "args": [
                                    {
                                        "column": "sensor_F"
                                    }
                                ],
                                "alias": "column_e6e50d1615248"
                            }
                        ],
                        "groups": [
                            {
                                "column": "timestamp"
                            }
                        ]
                    }
                },
                {
                    "id": "582375f1-8f82-49d6-a83f-88b989577a38",
                    "type": "CHART",
                    "name": "Histogram A",
                    "description": "",
                    "options": {
                        "version": 2,
                        "globalSeriesType": "histogram",
                        "sortX": true,
                        "sortY": true,
                        "legend": {
                            "traceorder": "normal"
                        },
                        "xAxis": {
                            "type": "-",
                            "labels": {
                                "enabled": true
                            }
                        },
                        "yAxis": [
                            {
                                "type": "-"
                            },
                            {
                                "type": "-",
                                "opposite": true
                            }
                        ],
                        "alignYAxesAtZero": true,
                        "error_y": {
                            "type": "data",
                            "visible": true
                        },
                        "series": {
                            "stacking": null,
                            "error_y": {
                                "type": "data",
                                "visible": true
                            }
                        },
                        "seriesOptions": {
                            "timestamp": {
                                "yAxis": 0,
                                "type": "histogram"
                            },
                            "COUNT": {
                                "color": "#5C62D6"
                            }
                        },
                        "valuesOptions": {},
                        "direction": {
                            "type": "counterclockwise"
                        },
                        "sizemode": "diameter",
                        "coefficient": 1,
                        "numberFormat": "0,0[.]00000",
                        "percentFormat": "0[.]00%",
                        "textFormat": "",
                        "missingValuesAsZero": true,
                        "useAggregationsUi": true,
                        "swappedAxes": false,
                        "dateTimeFormat": "YYYY-MM-DD HH:mm",
                        "showDataLabels": false,
                        "numBins": 100,
                        "columnConfigurationMap": {
                            "x": {
                                "column": "sensor_A",
                                "id": "column_e6e50d1616206"
                            }
                        },
                        "isAggregationOn": true
                    },
                    "query_plan": {
                        "selects": [
                            {
                                "function": "BIN",
                                "args": [
                                    {
                                        "column": "sensor_A"
                                    },
                                    {
                                        "number": 100.0
                                    }
                                ],
                                "alias": "sensor_A_BIN"
                            },
                            {
                                "function": "BIN_LOWER_BOUND",
                                "args": [
                                    {
                                        "column": "sensor_A"
                                    },
                                    {
                                        "number": 100.0
                                    }
                                ],
                                "alias": "sensor_A_BIN_LOWER_BOUND"
                            },
                            {
                                "function": "BIN_STEP",
                                "args": [
                                    {
                                        "column": "sensor_A"
                                    },
                                    {
                                        "number": 100.0
                                    }
                                ],
                                "alias": "sensor_A_BIN_STEP"
                            },
                            {
                                "function": "COUNT",
                                "args": [
                                    {
                                        "column": "sensor_A"
                                    }
                                ],
                                "alias": "COUNT"
                            }
                        ],
                        "groups": [
                            {
                                "column": "sensor_A_BIN"
                            }
                        ]
                    }
                },
                {
                    "id": "628fb25a-cbfa-430c-afc3-f30fd9f63aec",
                    "type": "CHART",
                    "name": "Histogram B",
                    "description": "",
                    "options": {
                        "version": 2,
                        "globalSeriesType": "histogram",
                        "sortX": true,
                        "sortY": true,
                        "legend": {
                            "traceorder": "normal"
                        },
                        "xAxis": {
                            "type": "-",
                            "labels": {
                                "enabled": true
                            }
                        },
                        "yAxis": [
                            {
                                "type": "-"
                            },
                            {
                                "type": "-",
                                "opposite": true
                            }
                        ],
                        "alignYAxesAtZero": true,
                        "error_y": {
                            "type": "data",
                            "visible": true
                        },
                        "series": {
                            "stacking": null,
                            "error_y": {
                                "type": "data",
                                "visible": true
                            }
                        },
                        "seriesOptions": {
                            "COUNT": {
                                "color": "#6B9AC4"
                            }
                        },
                        "valuesOptions": {},
                        "direction": {
                            "type": "counterclockwise"
                        },
                        "sizemode": "diameter",
                        "coefficient": 1,
                        "numberFormat": "0,0[.]00000",
                        "percentFormat": "0[.]00%",
                        "textFormat": "",
                        "missingValuesAsZero": true,
                        "useAggregationsUi": true,
                        "swappedAxes": false,
                        "dateTimeFormat": "YYYY-MM-DD HH:mm",
                        "showDataLabels": false,
                        "numBins": 100,
                        "columnConfigurationMap": {
                            "x": {
                                "column": "sensor_B",
                                "id": "column_e6e50d1616342"
                            }
                        },
                        "isAggregationOn": true
                    },
                    "query_plan": {
                        "selects": [
                            {
                                "function": "BIN",
                                "args": [
                                    {
                                        "column": "sensor_B"
                                    },
                                    {
                                        "number": 100.0
                                    }
                                ],
                                "alias": "sensor_B_BIN"
                            },
                            {
                                "function": "BIN_LOWER_BOUND",
                                "args": [
                                    {
                                        "column": "sensor_B"
                                    },
                                    {
                                        "number": 100.0
                                    }
                                ],
                                "alias": "sensor_B_BIN_LOWER_BOUND"
                            },
                            {
                                "function": "BIN_STEP",
                                "args": [
                                    {
                                        "column": "sensor_B"
                                    },
                                    {
                                        "number": 100.0
                                    }
                                ],
                                "alias": "sensor_B_BIN_STEP"
                            },
                            {
                                "function": "COUNT",
                                "args": [
                                    {
                                        "column": "sensor_B"
                                    }
                                ],
                                "alias": "COUNT"
                            }
                        ],
                        "groups": [
                            {
                                "column": "sensor_B_BIN"
                            }
                        ]
                    }
                },
                {
                    "id": "7ac05e2b-4c39-4533-b61b-fa42360ac448",
                    "type": "CHART",
                    "name": "Histogram D",
                    "description": "",
                    "options": {
                        "version": 2,
                        "globalSeriesType": "histogram",
                        "sortX": true,
                        "sortY": true,
                        "legend": {
                            "traceorder": "normal"
                        },
                        "xAxis": {
                            "type": "-",
                            "labels": {
                                "enabled": true
                            }
                        },
                        "yAxis": [
                            {
                                "type": "-"
                            },
                            {
                                "type": "-",
                                "opposite": true
                            }
                        ],
                        "alignYAxesAtZero": true,
                        "error_y": {
                            "type": "data",
                            "visible": true
                        },
                        "series": {
                            "stacking": null,
                            "error_y": {
                                "type": "data",
                                "visible": true
                            }
                        },
                        "seriesOptions": {},
                        "valuesOptions": {},
                        "direction": {
                            "type": "counterclockwise"
                        },
                        "sizemode": "diameter",
                        "coefficient": 1,
                        "numberFormat": "0,0[.]00000",
                        "percentFormat": "0[.]00%",
                        "textFormat": "",
                        "missingValuesAsZero": true,
                        "useAggregationsUi": true,
                        "swappedAxes": false,
                        "dateTimeFormat": "YYYY-MM-DD HH:mm",
                        "showDataLabels": false,
                        "numBins": 100,
                        "columnConfigurationMap": {
                            "x": {
                                "column": "sensor_D",
                                "id": "column_e6e50d1616503"
                            }
                        },
                        "isAggregationOn": true
                    },
                    "query_plan": {
                        "selects": [
                            {
                                "function": "BIN",
                                "args": [
                                    {
                                        "column": "sensor_D"
                                    },
                                    {
                                        "number": 100.0
                                    }
                                ],
                                "alias": "sensor_D_BIN"
                            },
                            {
                                "function": "BIN_LOWER_BOUND",
                                "args": [
                                    {
                                        "column": "sensor_D"
                                    },
                                    {
                                        "number": 100.0
                                    }
                                ],
                                "alias": "sensor_D_BIN_LOWER_BOUND"
                            },
                            {
                                "function": "BIN_STEP",
                                "args": [
                                    {
                                        "column": "sensor_D"
                                    },
                                    {
                                        "number": 100.0
                                    }
                                ],
                                "alias": "sensor_D_BIN_STEP"
                            },
                            {
                                "function": "COUNT",
                                "args": [
                                    {
                                        "column": "sensor_D"
                                    }
                                ],
                                "alias": "COUNT"
                            }
                        ],
                        "groups": [
                            {
                                "column": "sensor_D_BIN"
                            }
                        ]
                    }
                },
                {
                    "id": "7be5bc2c-fc33-4cfc-aea1-9e32e0d9c74e",
                    "type": "CHART",
                    "name": "Histogram C",
                    "description": "",
                    "options": {
                        "version": 2,
                        "globalSeriesType": "histogram",
                        "sortX": true,
                        "sortY": true,
                        "legend": {
                            "traceorder": "normal"
                        },
                        "xAxis": {
                            "type": "-",
                            "labels": {
                                "enabled": true
                            }
                        },
                        "yAxis": [
                            {
                                "type": "-"
                            },
                            {
                                "type": "-",
                                "opposite": true
                            }
                        ],
                        "alignYAxesAtZero": true,
                        "error_y": {
                            "type": "data",
                            "visible": true
                        },
                        "series": {
                            "stacking": null,
                            "error_y": {
                                "type": "data",
                                "visible": true
                            }
                        },
                        "seriesOptions": {},
                        "valuesOptions": {},
                        "direction": {
                            "type": "counterclockwise"
                        },
                        "sizemode": "diameter",
                        "coefficient": 1,
                        "numberFormat": "0,0[.]00000",
                        "percentFormat": "0[.]00%",
                        "textFormat": "",
                        "missingValuesAsZero": true,
                        "useAggregationsUi": true,
                        "swappedAxes": false,
                        "dateTimeFormat": "YYYY-MM-DD HH:mm",
                        "showDataLabels": false,
                        "numBins": 100,
                        "columnConfigurationMap": {
                            "x": {
                                "column": "sensor_C",
                                "id": "column_e6e50d1616386"
                            }
                        },
                        "isAggregationOn": true
                    },
                    "query_plan": {
                        "selects": [
                            {
                                "function": "BIN",
                                "args": [
                                    {
                                        "column": "sensor_C"
                                    },
                                    {
                                        "number": 100.0
                                    }
                                ],
                                "alias": "sensor_C_BIN"
                            },
                            {
                                "function": "BIN_LOWER_BOUND",
                                "args": [
                                    {
                                        "column": "sensor_C"
                                    },
                                    {
                                        "number": 100.0
                                    }
                                ],
                                "alias": "sensor_C_BIN_LOWER_BOUND"
                            },
                            {
                                "function": "BIN_STEP",
                                "args": [
                                    {
                                        "column": "sensor_C"
                                    },
                                    {
                                        "number": 100.0
                                    }
                                ],
                                "alias": "sensor_C_BIN_STEP"
                            },
                            {
                                "function": "COUNT",
                                "args": [
                                    {
                                        "column": "sensor_C"
                                    }
                                ],
                                "alias": "COUNT"
                            }
                        ],
                        "groups": [
                            {
                                "column": "sensor_C_BIN"
                            }
                        ]
                    }
                },
                {
                    "id": "83033fe6-7b50-429f-90da-3313ecadc0ef",
                    "type": "CHART",
                    "name": "Histogram E",
                    "description": "",
                    "options": {
                        "version": 2,
                        "globalSeriesType": "histogram",
                        "sortX": true,
                        "sortY": true,
                        "legend": {
                            "traceorder": "normal"
                        },
                        "xAxis": {
                            "type": "-",
                            "labels": {
                                "enabled": true
                            }
                        },
                        "yAxis": [
                            {
                                "type": "-"
                            },
                            {
                                "type": "-",
                                "opposite": true
                            }
                        ],
                        "alignYAxesAtZero": true,
                        "error_y": {
                            "type": "data",
                            "visible": true
                        },
                        "series": {
                            "stacking": null,
                            "error_y": {
                                "type": "data",
                                "visible": true
                            }
                        },
                        "seriesOptions": {
                            "COUNT": {
                                "color": "#97D8C4"
                            }
                        },
                        "valuesOptions": {},
                        "direction": {
                            "type": "counterclockwise"
                        },
                        "sizemode": "diameter",
                        "coefficient": 1,
                        "numberFormat": "0,0[.]00000",
                        "percentFormat": "0[.]00%",
                        "textFormat": "",
                        "missingValuesAsZero": true,
                        "useAggregationsUi": true,
                        "swappedAxes": false,
                        "dateTimeFormat": "YYYY-MM-DD HH:mm",
                        "showDataLabels": false,
                        "numBins": 100,
                        "columnConfigurationMap": {
                            "x": {
                                "column": "sensor_E",
                                "id": "column_e6e50d1616547"
                            }
                        },
                        "isAggregationOn": true
                    },
                    "query_plan": {
                        "selects": [
                            {
                                "function": "BIN",
                                "args": [
                                    {
                                        "column": "sensor_E"
                                    },
                                    {
                                        "number": 100.0
                                    }
                                ],
                                "alias": "sensor_E_BIN"
                            },
                            {
                                "function": "BIN_LOWER_BOUND",
                                "args": [
                                    {
                                        "column": "sensor_E"
                                    },
                                    {
                                        "number": 100.0
                                    }
                                ],
                                "alias": "sensor_E_BIN_LOWER_BOUND"
                            },
                            {
                                "function": "BIN_STEP",
                                "args": [
                                    {
                                        "column": "sensor_E"
                                    },
                                    {
                                        "number": 100.0
                                    }
                                ],
                                "alias": "sensor_E_BIN_STEP"
                            },
                            {
                                "function": "COUNT",
                                "args": [
                                    {
                                        "column": "sensor_E"
                                    }
                                ],
                                "alias": "COUNT"
                            }
                        ],
                        "groups": [
                            {
                                "column": "sensor_E_BIN"
                            }
                        ]
                    }
                },
                {
                    "id": "921161e0-6194-4614-9cdb-e683ea7048e7",
                    "type": "CHART",
                    "name": "Histogram F",
                    "description": "",
                    "options": {
                        "version": 2,
                        "globalSeriesType": "histogram",
                        "sortX": true,
                        "sortY": true,
                        "legend": {
                            "traceorder": "normal"
                        },
                        "xAxis": {
                            "type": "-",
                            "labels": {
                                "enabled": true
                            }
                        },
                        "yAxis": [
                            {
                                "type": "-"
                            },
                            {
                                "type": "-",
                                "opposite": true
                            }
                        ],
                        "alignYAxesAtZero": true,
                        "error_y": {
                            "type": "data",
                            "visible": true
                        },
                        "series": {
                            "stacking": null,
                            "error_y": {
                                "type": "data",
                                "visible": true
                            }
                        },
                        "seriesOptions": {
                            "COUNT": {
                                "color": "#F4B942"
                            }
                        },
                        "valuesOptions": {},
                        "direction": {
                            "type": "counterclockwise"
                        },
                        "sizemode": "diameter",
                        "coefficient": 1,
                        "numberFormat": "0,0[.]00000",
                        "percentFormat": "0[.]00%",
                        "textFormat": "",
                        "missingValuesAsZero": true,
                        "useAggregationsUi": true,
                        "swappedAxes": false,
                        "dateTimeFormat": "YYYY-MM-DD HH:mm",
                        "showDataLabels": false,
                        "numBins": 100,
                        "columnConfigurationMap": {
                            "x": {
                                "column": "sensor_F",
                                "id": "column_e6e50d1616664"
                            }
                        },
                        "isAggregationOn": true
                    },
                    "query_plan": {
                        "selects": [
                            {
                                "function": "BIN",
                                "args": [
                                    {
                                        "column": "sensor_F"
                                    },
                                    {
                                        "number": 100.0
                                    }
                                ],
                                "alias": "sensor_F_BIN"
                            },
                            {
                                "function": "BIN_LOWER_BOUND",
                                "args": [
                                    {
                                        "column": "sensor_F"
                                    },
                                    {
                                        "number": 100.0
                                    }
                                ],
                                "alias": "sensor_F_BIN_LOWER_BOUND"
                            },
                            {
                                "function": "BIN_STEP",
                                "args": [
                                    {
                                        "column": "sensor_F"
                                    },
                                    {
                                        "number": 100.0
                                    }
                                ],
                                "alias": "sensor_F_BIN_STEP"
                            },
                            {
                                "function": "COUNT",
                                "args": [
                                    {
                                        "column": "sensor_F"
                                    }
                                ],
                                "alias": "COUNT"
                            }
                        ],
                        "groups": [
                            {
                                "column": "sensor_F_BIN"
                            }
                        ]
                    }
                },
                {
                    "id": "a1cfd088-1cd6-46b4-84d6-727a22d23ce6",
                    "type": "CHART",
                    "name": "Sensor C",
                    "description": "",
                    "options": {
                        "version": 2,
                        "globalSeriesType": "line",
                        "sortX": true,
                        "sortY": true,
                        "legend": {
                            "traceorder": "normal"
                        },
                        "xAxis": {
                            "type": "-",
                            "labels": {
                                "enabled": true
                            }
                        },
                        "yAxis": [
                            {
                                "type": "-"
                            },
                            {
                                "type": "-",
                                "opposite": true
                            }
                        ],
                        "alignYAxesAtZero": true,
                        "error_y": {
                            "type": "data",
                            "visible": true
                        },
                        "series": {
                            "stacking": null,
                            "error_y": {
                                "type": "data",
                                "visible": true
                            }
                        },
                        "seriesOptions": {
                            "column_e6e50d1614047": {
                                "yAxis": 0,
                                "type": "line"
                            }
                        },
                        "valuesOptions": {},
                        "direction": {
                            "type": "counterclockwise"
                        },
                        "sizemode": "diameter",
                        "coefficient": 1,
                        "numberFormat": "0,0[.]00000",
                        "percentFormat": "0[.]00%",
                        "textFormat": "",
                        "missingValuesAsZero": true,
                        "useAggregationsUi": true,
                        "swappedAxes": false,
                        "dateTimeFormat": "YYYY-MM-DD HH:mm",
                        "showDataLabels": false,
                        "columnConfigurationMap": {
                            "x": {
                                "column": "timestamp",
                                "id": "column_e6e50d1614044"
                            },
                            "y": [
                                {
                                    "id": "column_e6e50d1614047",
                                    "column": "sensor_C",
                                    "transform": "SUM"
                                }
                            ]
                        },
                        "isAggregationOn": true,
                        "condensed": true,
                        "withRowNumber": true,
                        "hideYAxes": true
                    },
                    "query_plan": {
                        "selects": [
                            {
                                "column": "timestamp"
                            },
                            {
                                "function": "SUM",
                                "args": [
                                    {
                                        "column": "sensor_C"
                                    }
                                ],
                                "alias": "column_e6e50d1614047"
                            }
                        ],
                        "groups": [
                            {
                                "column": "timestamp"
                            }
                        ]
                    }
                },
                {
                    "id": "cb60fca1-0d2c-4b67-b2b8-ae7133be25bc",
                    "type": "CHART",
                    "name": "Sensor B",
                    "description": "",
                    "options": {
                        "version": 2,
                        "globalSeriesType": "line",
                        "sortX": true,
                        "sortY": true,
                        "legend": {
                            "traceorder": "normal"
                        },
                        "xAxis": {
                            "type": "-",
                            "labels": {
                                "enabled": true
                            }
                        },
                        "yAxis": [
                            {
                                "type": "-"
                            },
                            {
                                "type": "-",
                                "opposite": true
                            }
                        ],
                        "alignYAxesAtZero": true,
                        "error_y": {
                            "type": "data",
                            "visible": true
                        },
                        "series": {
                            "stacking": null,
                            "error_y": {
                                "type": "data",
                                "visible": true
                            }
                        },
                        "seriesOptions": {
                            "column_e6e50d1613918": {
                                "yAxis": 0,
                                "type": "line",
                                "color": "#6B9AC4"
                            }
                        },
                        "valuesOptions": {},
                        "direction": {
                            "type": "counterclockwise"
                        },
                        "sizemode": "diameter",
                        "coefficient": 1,
                        "numberFormat": "0,0[.]00000",
                        "percentFormat": "0[.]00%",
                        "textFormat": "",
                        "missingValuesAsZero": true,
                        "useAggregationsUi": true,
                        "swappedAxes": false,
                        "dateTimeFormat": "YYYY-MM-DD HH:mm",
                        "showDataLabels": false,
                        "columnConfigurationMap": {
                            "x": {
                                "column": "timestamp",
                                "id": "column_e6e50d1613916"
                            },
                            "y": [
                                {
                                    "id": "column_e6e50d1613918",
                                    "column": "sensor_B",
                                    "transform": "SUM"
                                }
                            ]
                        },
                        "isAggregationOn": true,
                        "condensed": true,
                        "withRowNumber": true,
                        "hideXAxis": false,
                        "hideYAxes": true
                    },
                    "query_plan": {
                        "selects": [
                            {
                                "column": "timestamp"
                            },
                            {
                                "function": "SUM",
                                "args": [
                                    {
                                        "column": "sensor_B"
                                    }
                                ],
                                "alias": "column_e6e50d1613918"
                            }
                        ],
                        "groups": [
                            {
                                "column": "timestamp"
                            }
                        ]
                    }
                },
                {
                    "id": "d30a25b5-f4df-42c4-9027-c0adee465c07",
                    "type": "CHART",
                    "name": "Energy produced",
                    "description": "",
                    "options": {
                        "version": 2,
                        "globalSeriesType": "area",
                        "sortX": true,
                        "sortY": true,
                        "legend": {
                            "traceorder": "normal"
                        },
                        "xAxis": {
                            "type": "-",
                            "labels": {
                                "enabled": true
                            }
                        },
                        "yAxis": [
                            {
                                "type": "-",
                                "title": {
                                    "text": "Instant energy produced"
                                }
                            },
                            {
                                "type": "-",
                                "opposite": true
                            }
                        ],
                        "alignYAxesAtZero": true,
                        "error_y": {
                            "type": "data",
                            "visible": true
                        },
                        "series": {
                            "stacking": null,
                            "error_y": {
                                "type": "data",
                                "visible": true
                            }
                        },
                        "seriesOptions": {
                            "column_e6e50d1615505": {
                                "yAxis": 0,
                                "type": "area"
                            }
                        },
                        "valuesOptions": {},
                        "direction": {
                            "type": "counterclockwise"
                        },
                        "sizemode": "diameter",
                        "coefficient": 1,
                        "numberFormat": "0,0[.]00000",
                        "percentFormat": "0[.]00%",
                        "textFormat": "",
                        "missingValuesAsZero": true,
                        "useAggregationsUi": true,
                        "swappedAxes": false,
                        "dateTimeFormat": "YYYY-MM-DD HH:mm",
                        "showDataLabels": false,
                        "columnConfigurationMap": {
                            "x": {
                                "column": "timestamp",
                                "id": "column_e6e50d1615502"
                            },
                            "y": [
                                {
                                    "id": "column_e6e50d1615505",
                                    "column": "energy",
                                    "transform": "SUM"
                                }
                            ]
                        },
                        "isAggregationOn": true,
                        "condensed": true,
                        "withRowNumber": true
                    },
                    "query_plan": {
                        "selects": [
                            {
                                "column": "timestamp"
                            },
                            {
                                "function": "SUM",
                                "args": [
                                    {
                                        "column": "energy"
                                    }
                                ],
                                "alias": "column_e6e50d1615505"
                            }
                        ],
                        "groups": [
                            {
                                "column": "timestamp"
                            }
                        ]
                    }
                },
                {
                    "id": "dbaa6737-c354-4657-95f1-d46e132b0763",
                    "type": "CHART",
                    "name": "sensor A",
                    "description": "",
                    "options": {
                        "version": 2,
                        "globalSeriesType": "line",
                        "sortX": true,
                        "sortY": true,
                        "legend": {
                            "traceorder": "normal"
                        },
                        "xAxis": {
                            "type": "-",
                            "labels": {
                                "enabled": true
                            }
                        },
                        "yAxis": [
                            {
                                "type": "-"
                            },
                            {
                                "type": "-",
                                "opposite": true
                            }
                        ],
                        "alignYAxesAtZero": true,
                        "error_y": {
                            "type": "data",
                            "visible": true
                        },
                        "series": {
                            "stacking": null,
                            "error_y": {
                                "type": "data",
                                "visible": true
                            },
                            "percentValues": false
                        },
                        "seriesOptions": {
                            "column_e6e50d1613351": {
                                "yAxis": 0,
                                "type": "line",
                                "color": "#5C62D6"
                            }
                        },
                        "valuesOptions": {},
                        "direction": {
                            "type": "counterclockwise"
                        },
                        "sizemode": "diameter",
                        "coefficient": 1,
                        "numberFormat": "0,0[.]00000",
                        "percentFormat": "0[.]00%",
                        "textFormat": "",
                        "missingValuesAsZero": true,
                        "useAggregationsUi": true,
                        "swappedAxes": false,
                        "dateTimeFormat": "YYYY-MM-DD HH:mm",
                        "showDataLabels": false,
                        "columnConfigurationMap": {
                            "x": {
                                "column": "timestamp",
                                "id": "column_e6e50d1613349"
                            },
                            "y": [
                                {
                                    "id": "column_e6e50d1613351",
                                    "column": "sensor_A",
                                    "transform": "SUM"
                                }
                            ]
                        },
                        "isAggregationOn": true,
                        "condensed": true,
                        "withRowNumber": true,
                        "hideYAxes": true
                    },
                    "query_plan": {
                        "selects": [
                            {
                                "column": "timestamp"
                            },
                            {
                                "function": "SUM",
                                "args": [
                                    {
                                        "column": "sensor_A"
                                    }
                                ],
                                "alias": "column_e6e50d1613351"
                            }
                        ],
                        "groups": [
                            {
                                "column": "timestamp"
                            }
                        ]
                    }
                },
                {
                    "id": "e42535f6-98f4-4a46-b236-2d4c2900e9b3",
                    "type": "TABLE",
                    "name": "Results",
                    "description": "",
                    "options": {
                        "version": 2
                    },
                    "query_plan": null
                },
                {
                    "id": "e831e49d-8e06-44f2-a186-3c669b6a5910",
                    "type": "CHART",
                    "name": "Sensor D",
                    "description": "",
                    "options": {
                        "version": 2,
                        "globalSeriesType": "line",
                        "sortX": true,
                        "sortY": true,
                        "legend": {
                            "traceorder": "normal"
                        },
                        "xAxis": {
                            "type": "-",
                            "labels": {
                                "enabled": true
                            }
                        },
                        "yAxis": [
                            {
                                "type": "-"
                            },
                            {
                                "type": "-",
                                "opposite": true
                            }
                        ],
                        "alignYAxesAtZero": true,
                        "error_y": {
                            "type": "data",
                            "visible": true
                        },
                        "series": {
                            "stacking": null,
                            "error_y": {
                                "type": "data",
                                "visible": true
                            }
                        },
                        "seriesOptions": {
                            "column_e6e50d1614172": {
                                "yAxis": 0,
                                "type": "line"
                            }
                        },
                        "valuesOptions": {},
                        "direction": {
                            "type": "counterclockwise"
                        },
                        "sizemode": "diameter",
                        "coefficient": 1,
                        "numberFormat": "0,0[.]00000",
                        "percentFormat": "0[.]00%",
                        "textFormat": "",
                        "missingValuesAsZero": true,
                        "useAggregationsUi": true,
                        "swappedAxes": false,
                        "dateTimeFormat": "YYYY-MM-DD HH:mm",
                        "showDataLabels": false,
                        "columnConfigurationMap": {
                            "x": {
                                "column": "timestamp",
                                "id": "column_e6e50d1614170"
                            },
                            "y": [
                                {
                                    "id": "column_e6e50d1614172",
                                    "column": "sensor_D",
                                    "transform": "SUM"
                                }
                            ]
                        },
                        "isAggregationOn": true,
                        "hideXAxis": false,
                        "hideYAxes": true,
                        "condensed": true,
                        "withRowNumber": true
                    },
                    "query_plan": {
                        "selects": [
                            {
                                "column": "timestamp"
                            },
                            {
                                "function": "SUM",
                                "args": [
                                    {
                                        "column": "sensor_D"
                                    }
                                ],
                                "alias": "column_e6e50d1614172"
                            }
                        ],
                        "groups": [
                            {
                                "column": "timestamp"
                            }
                        ]
                    }
                }
            ]
        },
        {
            "id": "09520323-73ae-4caa-a43e-6a497723b53e",
            "name": "IOT platform - turbine ids",
            "description": null,
            "query": "select distinct(turbine_id) from dbdemos_lakehouse_iot.turbine",
            "options": {
                "parent": "folders/2218726451409697",
                "apply_auto_limit": true,
                "folder_node_status": "ACTIVE",
                "folder_node_internal_name": "tree/2218726451419670",
                "visualization_control_order": [],
                "catalog": "hive_metastore",
                "schema": "dbdemos_lakehouse_iot",
                "parameters": []
            },
            "visualizations": [
                {
                    "id": "31b2b8e0-23e9-4648-a52b-ef88bc8920c2",
                    "type": "TABLE",
                    "name": "Results",
                    "description": "",
                    "options": {
                        "version": 2
                    },
                    "query_plan": null
                },
                {
                    "id": "761d3f70-2dca-4de3-bdfd-c96643ebd5c8",
                    "type": "TABLE",
                    "name": "Results",
                    "description": "",
                    "options": {
                        "version": 2
                    },
                    "query_plan": null
                }
            ]
        }
    ],
    "dashboard": {
        "id": "03051bc8-6bba-4f40-a198-e385930cd337",
        "name": "IOT Platform - Turbine analysis",
        "widgets": [
            {
                "id": "075b39ca-8068-410d-95bb-8cc3714182a1",
                "width": 1,
                "options": {
                    "parameterMappings": {
                        "turbine_id": {
                            "name": "turbine_id",
                            "type": "dashboard-level",
                            "mapTo": "turbine_id",
                            "value": null,
                            "title": ""
                        }
                    },
                    "title": "Sensor E - IOT platform - turbine sensors",
                    "description": "",
                    "isHidden": false,
                    "position": {
                        "autoHeight": false,
                        "sizeX": 4,
                        "sizeY": 5,
                        "minSizeX": 1,
                        "maxSizeX": 6,
                        "minSizeY": 5,
                        "maxSizeY": 1000,
                        "col": 0,
                        "row": 25
                    }
                },
                "dashboard_id": "03051bc8-6bba-4f40-a198-e385930cd337",
                "text": "",
                "visualization_id": "47f41294-0a31-4e1b-97fe-9d07e885fc7c"
            },
            {
                "id": "1ee866b6-389b-4ec0-b6ee-7df7b46de8ae",
                "width": 1,
                "options": {
                    "parameterMappings": {
                        "turbine_id": {
                            "name": "turbine_id",
                            "type": "dashboard-level",
                            "mapTo": "turbine_id",
                            "value": null,
                            "title": ""
                        }
                    },
                    "title": "Histogram F",
                    "description": "",
                    "isHidden": false,
                    "position": {
                        "autoHeight": false,
                        "sizeX": 2,
                        "sizeY": 5,
                        "minSizeX": 1,
                        "maxSizeX": 6,
                        "minSizeY": 5,
                        "maxSizeY": 1000,
                        "col": 4,
                        "row": 15
                    }
                },
                "dashboard_id": "03051bc8-6bba-4f40-a198-e385930cd337",
                "text": "",
                "visualization_id": "921161e0-6194-4614-9cdb-e683ea7048e7"
            },
            {
                "id": "24b41d96-6739-4c48-b18d-09949a8da691",
                "width": 1,
                "options": {
                    "parameterMappings": {
                        "turbine_id": {
                            "name": "turbine_id",
                            "type": "dashboard-level",
                            "mapTo": "turbine_id",
                            "value": null,
                            "title": ""
                        }
                    },
                    "title": "sensor A readings",
                    "description": "",
                    "isHidden": false,
                    "position": {
                        "autoHeight": false,
                        "sizeX": 4,
                        "sizeY": 5,
                        "minSizeX": 1,
                        "maxSizeX": 6,
                        "minSizeY": 5,
                        "maxSizeY": 1000,
                        "col": 0,
                        "row": 10
                    }
                },
                "dashboard_id": "03051bc8-6bba-4f40-a198-e385930cd337",
                "text": "",
                "visualization_id": "dbaa6737-c354-4657-95f1-d46e132b0763"
            },
            {
                "id": "709769c8-67f0-4d4e-9e44-132053883e65",
                "width": 1,
                "options": {
                    "parameterMappings": {
                        "turbine_id": {
                            "name": "turbine_id",
                            "type": "dashboard-level",
                            "mapTo": "turbine_id",
                            "value": null,
                            "title": ""
                        }
                    },
                    "title": "Histogram E",
                    "description": "",
                    "isHidden": false,
                    "position": {
                        "autoHeight": false,
                        "sizeX": 2,
                        "sizeY": 5,
                        "minSizeX": 1,
                        "maxSizeX": 6,
                        "minSizeY": 5,
                        "maxSizeY": 1000,
                        "col": 4,
                        "row": 25
                    }
                },
                "dashboard_id": "03051bc8-6bba-4f40-a198-e385930cd337",
                "text": "",
                "visualization_id": "83033fe6-7b50-429f-90da-3313ecadc0ef"
            },
            {
                "id": "e4eae69b-d906-45ac-b9d9-a43c681e5fff",
                "width": 1,
                "options": {
                    "parameterMappings": {
                        "turbine_id": {
                            "name": "turbine_id",
                            "type": "dashboard-level",
                            "mapTo": "turbine_id",
                            "value": null,
                            "title": ""
                        }
                    },
                    "title": "Status - IOT platform - turbine status",
                    "description": "",
                    "isHidden": false,
                    "position": {
                        "autoHeight": false,
                        "sizeX": 2,
                        "sizeY": 4,
                        "minSizeX": 1,
                        "maxSizeX": 6,
                        "minSizeY": 1,
                        "maxSizeY": 1000,
                        "col": 4,
                        "row": 0
                    }
                },
                "dashboard_id": "03051bc8-6bba-4f40-a198-e385930cd337",
                "text": "",
                "visualization_id": "0d972d3c-2093-4689-bd4d-8792964381b7"
            },
            {
                "id": "4066ac58-27a7-4b70-9e66-5c906be3201b",
                "width": 1,
                "options": {
                    "parameterMappings": {
                        "turbine_id": {
                            "name": "turbine_id",
                            "type": "dashboard-level",
                            "mapTo": "turbine_id",
                            "value": null,
                            "title": ""
                        }
                    },
                    "title": "Map - IOT platform - turbine status",
                    "description": "",
                    "isHidden": false,
                    "position": {
                        "autoHeight": false,
                        "sizeX": 2,
                        "sizeY": 6,
                        "minSizeX": 2,
                        "maxSizeX": 6,
                        "minSizeY": 1,
                        "maxSizeY": 1000,
                        "col": 4,
                        "row": 4
                    }
                },
                "dashboard_id": "03051bc8-6bba-4f40-a198-e385930cd337",
                "text": "",
                "visualization_id": "7cca4f40-d382-4e6a-94b3-3133a89456ea"
            },
            {
                "id": "9be93941-f57f-425d-80a5-166107b89140",
                "width": 1,
                "options": {
                    "parameterMappings": {
                        "turbine_id": {
                            "name": "turbine_id",
                            "type": "dashboard-level",
                            "mapTo": "turbine_id",
                            "value": null,
                            "title": ""
                        }
                    },
                    "title": "Energy produced",
                    "description": "",
                    "isHidden": false,
                    "position": {
                        "autoHeight": false,
                        "sizeX": 4,
                        "sizeY": 6,
                        "minSizeX": 1,
                        "maxSizeX": 6,
                        "minSizeY": 5,
                        "maxSizeY": 1000,
                        "col": 0,
                        "row": 4
                    }
                },
                "dashboard_id": "03051bc8-6bba-4f40-a198-e385930cd337",
                "text": "",
                "visualization_id": "d30a25b5-f4df-42c4-9027-c0adee465c07"
            },
            {
                "id": "c5eff73d-8033-4419-9140-4312fa7dd7aa",
                "width": 1,
                "options": {
                    "parameterMappings": {
                        "turbine_id": {
                            "name": "turbine_id",
                            "type": "dashboard-level",
                            "mapTo": "turbine_id",
                            "value": null,
                            "title": ""
                        }
                    },
                    "title": "Sensor F - IOT platform - turbine sensors",
                    "description": "",
                    "isHidden": false,
                    "position": {
                        "autoHeight": false,
                        "sizeX": 4,
                        "sizeY": 5,
                        "minSizeX": 1,
                        "maxSizeX": 6,
                        "minSizeY": 5,
                        "maxSizeY": 1000,
                        "col": 0,
                        "row": 15
                    }
                },
                "dashboard_id": "03051bc8-6bba-4f40-a198-e385930cd337",
                "text": "",
                "visualization_id": "5277fafd-49bb-447c-9f59-697059c3293a"
            },
            {
                "id": "e24535b3-0741-4af9-ab13-7242f91bac43",
                "width": 1,
                "options": {
                    "parameterMappings": {
                        "turbine_id": {
                            "name": "turbine_id",
                            "type": "dashboard-level",
                            "mapTo": "turbine_id",
                            "value": null,
                            "title": ""
                        }
                    },
                    "title": "Histogram B",
                    "description": "",
                    "isHidden": false,
                    "position": {
                        "autoHeight": false,
                        "sizeX": 2,
                        "sizeY": 5,
                        "minSizeX": 1,
                        "maxSizeX": 6,
                        "minSizeY": 5,
                        "maxSizeY": 1000,
                        "col": 4,
                        "row": 20
                    },
                    "overrideColors": false
                },
                "dashboard_id": "03051bc8-6bba-4f40-a198-e385930cd337",
                "text": "",
                "visualization_id": "628fb25a-cbfa-430c-afc3-f30fd9f63aec"
            },
            {
                "id": "ffbc7563-86f2-48ce-89cf-66257316597e",
                "width": 1,
                "options": {
                    "parameterMappings": {
                        "turbine_id": {
                            "name": "turbine_id",
                            "type": "dashboard-level",
                            "mapTo": "turbine_id",
                            "value": null,
                            "title": ""
                        }
                    },
                    "title": "Sensor B readings",
                    "description": "",
                    "isHidden": false,
                    "position": {
                        "autoHeight": false,
                        "sizeX": 4,
                        "sizeY": 5,
                        "minSizeX": 1,
                        "maxSizeX": 6,
                        "minSizeY": 5,
                        "maxSizeY": 1000,
                        "col": 0,
                        "row": 20
                    }
                },
                "dashboard_id": "03051bc8-6bba-4f40-a198-e385930cd337",
                "text": "",
                "visualization_id": "cb60fca1-0d2c-4b67-b2b8-ae7133be25bc"
            },
            {
                "id": "515b8821-45e2-45da-9537-e4a11dd70196",
                "width": 1,
                "options": {
                    "parameterMappings": {
                        "turbine_id": {
                            "name": "turbine_id",
                            "type": "dashboard-level",
                            "mapTo": "turbine_id",
                            "value": null,
                            "title": ""
                        }
                    },
                    "title": "energy - IOT platform - turbine status",
                    "description": "",
                    "isHidden": false,
                    "position": {
                        "autoHeight": false,
                        "sizeX": 2,
                        "sizeY": 4,
                        "minSizeX": 1,
                        "maxSizeX": 6,
                        "minSizeY": 1,
                        "maxSizeY": 1000,
                        "col": 0,
                        "row": 0
                    }
                },
                "dashboard_id": "03051bc8-6bba-4f40-a198-e385930cd337",
                "text": "",
                "visualization_id": "ca63688a-7d8c-40b4-9177-c891408e8799"
            },
            {
                "id": "b8b01292-3ffd-4f64-ba68-ad0e12f98266",
                "width": 1,
                "options": {
                    "parameterMappings": {
                        "turbine_id": {
                            "name": "turbine_id",
                            "type": "dashboard-level",
                            "mapTo": "turbine_id",
                            "value": null,
                            "title": ""
                        }
                    },
                    "title": "Histogram A - IOT platform - turbine sensors",
                    "description": "",
                    "isHidden": false,
                    "position": {
                        "autoHeight": false,
                        "sizeX": 2,
                        "sizeY": 5,
                        "minSizeX": 1,
                        "maxSizeX": 6,
                        "minSizeY": 5,
                        "maxSizeY": 1000,
                        "col": 4,
                        "row": 10
                    },
                    "overrideColors": false
                },
                "dashboard_id": "03051bc8-6bba-4f40-a198-e385930cd337",
                "text": "",
                "visualization_id": "582375f1-8f82-49d6-a83f-88b989577a38"
            },
            {
                "id": "bc144b33-935b-43db-aed2-c7592213493c",
                "width": 1,
                "options": {
                    "parameterMappings": {
                        "turbine_id": {
                            "name": "turbine_id",
                            "type": "dashboard-level",
                            "mapTo": "turbine_id",
                            "value": null,
                            "title": ""
                        }
                    },
                    "title": "Model - IOT platform - turbine status",
                    "description": "",
                    "isHidden": false,
                    "position": {
                        "autoHeight": false,
                        "sizeX": 2,
                        "sizeY": 4,
                        "minSizeX": 1,
                        "maxSizeX": 6,
                        "minSizeY": 1,
                        "maxSizeY": 1000,
                        "col": 2,
                        "row": 0
                    }
                },
                "dashboard_id": "03051bc8-6bba-4f40-a198-e385930cd337",
                "text": "",
                "visualization_id": "aef2e0a6-2265-41ec-8a01-1310cd97c40c"
            }
        ],
        "tags": [
            "field_demos",
            "field_demos_manufacturing",
            "wind_turbine"
        ],
        "color_palette": null,
        "dashboard_filters_enabled": false,
        "parent": "folders/2218726451409697",
        "is_archived": false
    },
    "version": "1.0"
}